odoo/addons/in_memory_filestore/__init__.py
odoo/addons/in_memory_filestore/__manifest__.py
odoo/addons/in_memory_filestore/data/ir_config_parameter.xml
odoo12_addon_in_memory_filestore-12.0.1.0.3.dist-info/METADATA
odoo12_addon_in_memory_filestore-12.0.1.0.3.dist-info/WHEEL
odoo12_addon_in_memory_filestore-12.0.1.0.3.dist-info/top_level.txt
odoo12_addon_in_memory_filestore-12.0.1.0.3.dist-info/RECORD
